easy_versioning/__init__.py
easy_versioning/main.py
easy_versioning/data/footer.html
easy_versioning-1.0.8.dist-info/licenses/LICENSE
easy_versioning-1.0.8.dist-info/METADATA
easy_versioning-1.0.8.dist-info/WHEEL
easy_versioning-1.0.8.dist-info/entry_points.txt
easy_versioning-1.0.8.dist-info/top_level.txt
easy_versioning-1.0.8.dist-info/RECORD
