Metadata-Version: 2.4
Name: Easy_versioning
Version: 1.0.8
Summary: A Sphinx extension/tool to manage multi-version and multi-language documentation builds without relying on ReadTheDocs.
Author-email: Niccolò Quadrani <niccoloquadrani13@gmail.com>
License-Expression: MIT
Project-URL: Homepage, https://github.com/Quadra-Ryo/Easy-versioning-sphinx
Project-URL: Issues, https://github.com/Quadra-Ryo/Easy-versioning-sphinx/issues
Keywords: sphinx,documentation,versioning,multi-language,RTD,Read The Docs
Requires-Python: >=3.8
License-File: LICENSE
Requires-Dist: termcolor>=2.0
Requires-Dist: sphinx>=6.0
Dynamic: license-file
